fhir_mcp_server/__init__.py
fhir_mcp_server/server.py
fhir_mcp_server/utils.py
fhir_mcp_server/oauth/__init__.py
fhir_mcp_server/oauth/client_provider.py
fhir_mcp_server/oauth/common.py
fhir_mcp_server/oauth/server_provider.py
fhir_mcp_server/oauth/types.py
fhir_mcp_server-1.0.1.dist-info/METADATA
fhir_mcp_server-1.0.1.dist-info/WHEEL
fhir_mcp_server-1.0.1.dist-info/entry_points.txt
fhir_mcp_server-1.0.1.dist-info/licenses/LICENSE
fhir_mcp_server-1.0.1.dist-info/RECORD
