Metadata-Version: 2.4
Name: fhir-mcp-server
Version: 1.0.1
Summary: A Model Context Protocol (MCP) server that provides seamless, standardized access to Fast Healthcare Interoperability Resources (FHIR) data from any compatible FHIR server. Designed for easy integration with AI tools, developer workflows, and healthcare applications, it enables natural language and programmatic search, retrieval, and analysis of clinical data.
Project-URL: Bug Tracker, https://github.com/wso2/fhir-mcp-server/issues
Project-URL: Documentation, https://github.com/wso2/fhir-mcp-server/blob/development/README.md
Project-URL: Homepage, https://github.com/wso2/fhir-mcp-server
Author-email: WSO2 <dev@wso2.org>
License-Expression: Apache-2.0
License-File: LICENSE
Keywords: fhir,healthcare,llm,mcp,model-context-protocol
Classifier: Development Status :: 4 - Beta
Classifier: Intended Audience :: Developers
Classifier: Operating System :: OS Independent
Classifier: Programming Language :: Python :: 3
Classifier: Programming Language :: Python :: 3.12
Requires-Python: >=3.12
Requires-Dist: aiohttp>=3.12.13
Requires-Dist: fhirpy>=2.0.15
Requires-Dist: mcp[cli]>=1.9.1
